ceres/__main__.py
ceres/__test__.py
ceres/polaris.py
polaris_python_bzl-0.0.3.dist-info/METADATA
polaris_python_bzl-0.0.3.dist-info/WHEEL
polaris_python_bzl-0.0.3.dist-info/RECORD
